{
  "battlescene.gezi": "XNw+yaUZng58u651CvnaMw==",
  "bullet.gezi": "bRFjQUhcn9+h8iZiB0VwgQ==",
  "bullet1.gezi": "fp6l1yTLEkeghiowgBwh1Q==",
  "cardtex.gezi": "fkIB6xuTmJYerL04Vfd8bQ==",
  "charactar.gezi": "onD9bsIfVofV1gMGRurQ2w==",
  "coin.gezi": "6HcHiZGngGYwzJ3lYFfaXg==",
  "fieldandstate.gezi": "c/Ev6RC3nZdHc994B1Nrog==",
  "gamedata.gezi": "G8LJsIEo+vPxKa8hDiqOsw==",
  "icon.gezi": "/DLLt+bv9uf2hqWgPv8mFw==",
  "loginscene.gezi": "6HKRu9eCPDHBUFHHyfVKJw==",
  "particle.gezi": "sz34i6kzjvNmWZOMMvqreA==",
  "prefabs.gezi": "u7U7IonYDjiR+72UGmkg5g==",
  "scene.gezi": "0IviLm7leNR/dYmVv5e6zw==",
  "scene1.gezi": "YXD8e+/veiIS7o3FPld+Ug==",
  "scene2.gezi": "FddQ3HVwXq7pNRH7fTxvUA==",
  "shader_material.gezi": "1mG6uWvpINEnDZU//I5J0w==",
  "soundeffect.gezi": "7dex9QzJ5iN2A68PXY+QoQ==",
  "texture.gezi": "yOVtqAcTuBewRaaO9P0hgQ==",
  "TouHouMachineLearning.dll": "H3J6YJCeM2q7IWhQS9BeFQ==",
  "ttf.gezi": "FWniCM0++xs4iuzi6Fvopw==",
  "uitexture.gezi": "c+nOuEuEFLDdzxTuuCNfxA=="
}